spotify_mcp/__about__.py
spotify_mcp/__init__.py
spotify_mcp/server.py
spotify_mcp/spotify_api.py
spotify_mcp/utils.py
spotify_mcp_bico13-0.2.1.dist-info/METADATA
spotify_mcp_bico13-0.2.1.dist-info/WHEEL
spotify_mcp_bico13-0.2.1.dist-info/entry_points.txt
spotify_mcp_bico13-0.2.1.dist-info/RECORD
